odoo10_addon_l10n_ch_account_reconcile_isr-10.0.1.1.0-nspkg.pth
odoo/addons/l10n_ch_account_reconcile_isr/README.rst
odoo/addons/l10n_ch_account_reconcile_isr/__init__.py
odoo/addons/l10n_ch_account_reconcile_isr/__manifest__.py
odoo/addons/l10n_ch_account_reconcile_isr/i18n/de.po
odoo/addons/l10n_ch_account_reconcile_isr/i18n/fr.po
odoo/addons/l10n_ch_account_reconcile_isr/i18n/it.po
odoo/addons/l10n_ch_account_reconcile_isr/i18n/l10n_ch_account_reconcile_isr.pot
odoo/addons/l10n_ch_account_reconcile_isr/models/__init__.py
odoo/addons/l10n_ch_account_reconcile_isr/models/account_bank_statement_line.py
odoo/addons/l10n_ch_account_reconcile_isr/models/bank_statement.py
odoo/addons/l10n_ch_account_reconcile_isr/readme/CONTRIBUTORS.rst
odoo/addons/l10n_ch_account_reconcile_isr/readme/DESCRIPTION.rst
odoo/addons/l10n_ch_account_reconcile_isr/readme/USAGE.rst
odoo/addons/l10n_ch_account_reconcile_isr/static/description/icon.png
odoo/addons/l10n_ch_account_reconcile_isr/static/description/index.html
odoo/addons/l10n_ch_account_reconcile_isr/static/src/js/account_reconciliation.js
odoo/addons/l10n_ch_account_reconcile_isr/static/src/xml/account_reconciliation.xml
odoo/addons/l10n_ch_account_reconcile_isr/views/assets.xml
odoo10_addon_l10n_ch_account_reconcile_isr-10.0.1.1.0.dist-info/METADATA
odoo10_addon_l10n_ch_account_reconcile_isr-10.0.1.1.0.dist-info/WHEEL
odoo10_addon_l10n_ch_account_reconcile_isr-10.0.1.1.0.dist-info/namespace_packages.txt
odoo10_addon_l10n_ch_account_reconcile_isr-10.0.1.1.0.dist-info/top_level.txt
odoo10_addon_l10n_ch_account_reconcile_isr-10.0.1.1.0.dist-info/RECORD
