Metadata-Version: 2.1
Name: odoo10-addon-l10n-ch-account-reconcile-isr
Version: 10.0.1.1.0
Summary: Adds a second automatic reconciliation button, which is based on the isr
Home-page: https://github.com/OCA/l10n-switzerland
Author: Camptocamp,Odoo Community Association (OCA)
Author-email: support@odoo-community.org
License: AGPL-3
Platform: UNKNOWN
Classifier: Programming Language :: Python
Classifier: Framework :: Odoo
Classifier: License :: OSI Approved :: GNU Affero General Public License v3
Requires-Python: ~=2.7
Requires-Dist: odoo10-addon-base-transaction-id
Requires-Dist: odoo (<10.1dev,>=10.0)
